Titanicbc/Binary_Network.py
Titanicbc/__init__.py
Titanicbc/__main__.py
Titanicbc/config.yaml
Titanicbc/output.csv
Titanicbc/test.csv
Titanicbc/train.csv
Titanicbc/trained_model.pth
Titanicbc-2.0.7.dist-info/METADATA
Titanicbc-2.0.7.dist-info/WHEEL
Titanicbc-2.0.7.dist-info/top_level.txt
Titanicbc-2.0.7.dist-info/RECORD
