Metadata-Version: 2.1
Name: Titanicbc
Version: 2.0.7
Summary: Simple neural network interface including pre-trained model for the Kaggle Titanic dataset
Home-page: https://github.com/chrisb27/Titanic_Binary
Author: Christopher Burton
Author-email: chrisburton279@gmail.com
License: UNKNOWN
Platform: UNKNOWN
Requires-Dist: docutils (>=0.3)
Requires-Dist: torch (>=1.5.0)
Requires-Dist: pandas (>=1.0.3)
Requires-Dist: matplotlib (>=3.2.1)
